lamin_logger/__init__.py
lamin_logger/_core.py
lamin_logger-0.1.1.dist-info/WHEEL
lamin_logger-0.1.1.dist-info/METADATA
lamin_logger-0.1.1.dist-info/RECORD
