Metadata-Version: 2.1
Name: lamin_logger
Version: 0.1.1
Summary: Logging setup.
Author-email: Lamin Labs <laminlabs@gmail.com>
Requires-Dist: nbproject
Requires-Dist: loguru
Requires-Dist: pre-commit ; extra == "dev"
Requires-Dist: nox ; extra == "dev"
Requires-Dist: pytest>=6.0 ; extra == "test"
Requires-Dist: pytest-cov ; extra == "test"
Project-URL: Home, https://github.com/laminlabs/lamin-logger
Provides-Extra: dev
Provides-Extra: test
